README.md
setup.cfg
setup.py
rspec/__init__.py
rspec.egg-info/PKG-INFO
rspec.egg-info/SOURCES.txt
rspec.egg-info/dependency_links.txt
rspec.egg-info/entry_points.txt
rspec.egg-info/requires.txt
rspec.egg-info/top_level.txt
rspec/cli/__init__.py
rspec/cli/database.py
rspec/cli/decompose.py
rspec/composition/__init__.py
rspec/composition/lstsq.py
rspec/filter/__init__.py
rspec/filter/range.py
rspec/io/__init__.py
rspec/io/database.py
rspec/io/thermo.py
rspec/visualize/__init__.py
rspec/visualize/plotly.py