Metadata-Version: 2.1
Name: rspec
Version: 0.0.1
Summary: A Python image processing package for LLSM.
Home-page: https://github.com/liuyenting/rspec
Author: Liu, Yen-Ting
License: UNKNOWN
Platform: UNKNOWN
Classifier: Development Status :: 3 - Alpha
Classifier: License :: OSI Approved :: Apache Software License
Classifier: Operating System :: MacOS
Classifier: Operating System :: Microsoft :: Windows
Classifier: Operating System :: POSIX :: Linux
Classifier: Programming Language :: Python :: 3
Classifier: Topic :: Scientific/Engineering
Classifier: Intended Audience :: Developers
Classifier: Intended Audience :: End Users/Desktop
Classifier: Intended Audience :: Science/Research
Requires-Python: >=3.6
